README.rst
screenshot.png
setup.py
woodexperience.zip
docs/HISTORY.txt
docs/INSTALL.txt
docs/LICENSE.GPL
docs/LICENSE.txt
plonetheme/__init__.py
plonetheme.woodexperience.egg-info/PKG-INFO
plonetheme.woodexperience.egg-info/SOURCES.txt
plonetheme.woodexperience.egg-info/dependency_links.txt
plonetheme.woodexperience.egg-info/entry_points.txt
plonetheme.woodexperience.egg-info/namespace_packages.txt
plonetheme.woodexperience.egg-info/requires.txt
plonetheme.woodexperience.egg-info/top_level.txt
plonetheme/woodexperience/__init__.py
plonetheme/woodexperience/configure.zcml
plonetheme/woodexperience/profiles/default/metadata.xml
plonetheme/woodexperience/profiles/default/theme.xml
plonetheme/woodexperience/static/index.html
plonetheme/woodexperience/static/license.txt
plonetheme/woodexperience/static/manifest.cfg
plonetheme/woodexperience/static/plone-integration.css
plonetheme/woodexperience/static/readme.txt
plonetheme/woodexperience/static/rules.xml
plonetheme/woodexperience/static/css/default.css
plonetheme/woodexperience/static/css/print.css
plonetheme/woodexperience/static/images/bg-body.png
plonetheme/woodexperience/static/images/bg-foot.png
plonetheme/woodexperience/static/images/bg-list.gif
plonetheme/woodexperience/static/images/bg-logo.jpg
plonetheme/woodexperience/static/images/bg-main.jpg
plonetheme/woodexperience/static/images/bg-view.png
plonetheme/woodexperience/static/images/frame.gif
plonetheme/woodexperience/static/images/ico/ico-breezy-hover.gif
plonetheme/woodexperience/static/images/ico/ico-breezy.gif
plonetheme/woodexperience/static/img/image1.jpg
plonetheme/woodexperience/static/img/image2.jpg
plonetheme/woodexperience/static/img/image3.jpg
plonetheme/woodexperience/static/js/imagelink.js